scribe_updater/__init__.py
scribe_updater/changelog.py
scribe_updater/console.py
scribe_updater/product.py
scribe_updater/updater.py
scribe_updater/utils.py
scribe_updater/version_mapping/3.3_to_3.5.json
scribe_updater/version_mapping/3.3_to_3.6.json
scribe_updater/version_mapping/3.3_to_3.7.json
scribe_updater/version_mapping/3.3_to_3.9.json
scribe_updater/version_mapping/4.0_to_4.1.json
scribe_updater-0.17.3.dist-info/entry_points.txt
scribe_updater-0.17.3.dist-info/WHEEL
scribe_updater-0.17.3.dist-info/METADATA
scribe_updater-0.17.3.dist-info/RECORD
