Metadata-Version: 2.1
Name: scribe-updater
Version: 0.17.3
Summary: A tool to upgrade scribe configuration files
Author: Paul Cardoos
Author-email: paul.cardoos@clinc.com
Requires-Python: >=3.7,<4.0
Classifier: Programming Language :: Python :: 3
Classifier: Programming Language :: Python :: 3.7
Classifier: Programming Language :: Python :: 3.8
Classifier: Programming Language :: Python :: 3.9
Classifier: Programming Language :: Python :: 3.10
Classifier: Programming Language :: Python :: 3.11
Requires-Dist: click (>=8.1.3,<9.0.0)
Requires-Dist: nox (>=2022.11.21,<2023.0.0)
